pddiktipy/__init__.py
pddiktipy/api.py
pddiktipy/exceptions.py
pddiktipy/helper.py
pddiktipy-2.0.6.dist-info/licenses/LICENSE
pddiktipy-2.0.6.dist-info/METADATA
pddiktipy-2.0.6.dist-info/WHEEL
pddiktipy-2.0.6.dist-info/top_level.txt
pddiktipy-2.0.6.dist-info/RECORD
