Metadata-Version: 2.4
Name: pddiktipy
Version: 2.0.6
Summary: Unofficial Python API wrapper to get data at PDDIKTI Kemdikbud
Home-page: https://github.com/IlhamriSKY/PDDIKTI-kemdikbud-API
Author: Ilham Riski Wibowo
Author-email: ilhamrisky21@gmail.com
License: MIT
Project-URL: Homepage, https://github.com/IlhamriSKY/PDDIKTI-kemdikbud-API
Project-URL: Repository, https://github.com/IlhamriSKY/PDDIKTI-kemdikbud-API
Project-URL: Issues, https://github.com/IlhamriSKY/PDDIKTI-kemdikbud-API/issues
Project-URL: Documentation, https://github.com/IlhamriSKY/PDDIKTI-kemdikbud-API#readme
Keywords: pddikti,api,education,indonesia,kemdikbud,data
Classifier: Development Status :: 4 - Beta
Classifier: Intended Audience :: Science/Research
Classifier: Intended Audience :: Education
Classifier: Programming Language :: Python :: 3
Classifier: Programming Language :: Python :: 3.7
Classifier: Programming Language :: Python :: 3.8
Classifier: Programming Language :: Python :: 3.9
Classifier: Programming Language :: Python :: 3.10
Classifier: Programming Language :: Python :: 3.11
Classifier: Programming Language :: Python :: 3.12
Classifier: Programming Language :: Python :: 3.13
Classifier: Operating System :: OS Independent
Classifier: Topic :: Education
Classifier: Topic :: Scientific/Engineering :: Information Analysis
Classifier: Topic :: Software Development :: Libraries :: Python Modules
Classifier: License :: OSI Approved :: MIT License
Requires-Python: >=3.7
License-File: LICENSE
Requires-Dist: requests>=2.25.0
Dynamic: author
Dynamic: author-email
Dynamic: classifier
Dynamic: description
Dynamic: description-content-type
Dynamic: home-page
Dynamic: keywords
Dynamic: license
Dynamic: license-file
Dynamic: project-url
Dynamic: requires-dist
Dynamic: requires-python
Dynamic: summary
